setup.py
myna/__init__.py
myna/shim.py
python_myna.egg-info/PKG-INFO
python_myna.egg-info/SOURCES.txt
python_myna.egg-info/dependency_links.txt
python_myna.egg-info/top_level.txt