Metadata-Version: 1.1
Name: python-myna
Version: 1.0.1
Summary: Using the Myna process virtualisation testing tool from Python unit tests
Home-page: https://github.com/SpectoLabs/myna
Author: SpectoLabs
Author-email: admin@specto.io
License: UNKNOWN
Platform: UNKNOWN
Classifier: Programming Language :: Python
